Metadata-Version: 2.1
Name: algoliasearch-django
Version: 3.0.0
Summary: Algolia Search integration for Django
Home-page: https://github.com/algolia/algoliasearch-django
Author: Algolia Team
Author-email: support@algolia.com
License: MIT License
Keywords: algolia,pyalgolia,search,backend,hosted,cloud,full-text search,faceted search,django
Classifier: Environment :: Web Environment
Classifier: Framework :: Django
Classifier: Intended Audience :: Developers
Classifier: License :: OSI Approved :: MIT License
Classifier: Operating System :: OS Independent
Classifier: Programming Language :: Python
Classifier: Programming Language :: Python :: 2
Classifier: Programming Language :: Python :: 3
Classifier: Topic :: Internet :: WWW/HTTP
License-File: LICENSE
